rlink/__init__.py
rlink/bus.py
rlink/module.py
rlink/relay2ch.py
hc_rlink-1.0.0.dist-info/METADATA
hc_rlink-1.0.0.dist-info/WHEEL
hc_rlink-1.0.0.dist-info/top_level.txt
hc_rlink-1.0.0.dist-info/RECORD
