Metadata-Version: 2.4
Name: hc-rlink
Version: 1.0.0
Summary: Python library to control Hobby Components rLink RS485 modules
Home-page: https://hobbycomponents.com/rlink
Author: HobbyComponents (Andrew Davies)
Author-email: support@hobbycomponents.com
Classifier: Programming Language :: Python :: 3
Classifier: License :: OSI Approved :: MIT License
Classifier: Operating System :: POSIX :: Linux
Requires-Python: >=3.6
Requires-Dist: pyserial>=3.4
Requires-Dist: RPi.GPIO>=0.7
Dynamic: author
Dynamic: author-email
Dynamic: classifier
Dynamic: description
Dynamic: description-content-type
Dynamic: home-page
Dynamic: requires-dist
Dynamic: requires-python
Dynamic: summary
